Full_Adder/full_adder.v
module full_adder 
(
    input a, b, c,
    output carry, sum //assigning inputs and outputs 
);
    assign carry = ((a ^ b) & c) | (a & b); //makign carry eqaul to the carry bool equation 
    assign sum = ((a ^ b) ^ c); //making sum equal to the sum bool equation for full adder
endmodule

Learning Verilog/Adder_4bit/adder_4bit.v
module adder_4bit
(
    input [3:0] a, b, 
    input carry_in, 
    output [3:0] sum,
    output carry_out
); 

    wire c0, c1, c2; 

    full_adder fa0 
    (
        .a(a[0]),
        .b(b[0]),
        .c(carry_in),
        .sum(sum[0]),
        .carry(c0)
    );

    full_adder fa1 
    (
        .a(a[1]),
        .b(b[1]),
        .c(carry_in),
        .sum(sum[1]),
        .carry(c1)
    );

    full_adder fa2 
    (
        .a(a[2]),
        .b(b[2]),
        .c(carry_in),
        .sum(sum[2]),
        .carry(c2)
    );

    full_adder fa3
    (
        .a(a[3]),
        .b(b[3]),
        .c(carry_in),
        .sum(sum[3]),
        .carry(carry_out)
    );

endmodule

Learning Verilog/Adder_4bit/adder_4bit_tb.v
module adder_4bit_tb();

    reg [3:0] a, b;
    reg carry_in;
    wire [3:0] sum;
    wire carry_out; 

    integer i;
    reg [4:0] expected;

    adder_4bit uut
    (
        .a(a),
        .b(b),
        .carry_in(carry_in),
        .sum(sum),
        .carry_out(carry_out)
    );

    initial begin

        $dumpfile("adder_4bit.vcd");
        $dumpvars(0, adder_4bit_tb);

        for (i = 0; i < 512; i = i + 1) begin
            {carry_in, a, b} = i;
            #10;

        end

        $finish;

    end

endmodule

Adder_4bit/adder_4bit.vcd
$date
	Wed Jun 17 00:14:35 2026
$end
$version
	Icarus Verilog
$end
$timescale
	1s
$end
$scope module adder_4bit_tb $end
$var wire 4 ! sum [3:0] $end
$var wire 1 " carry_out $end
$var reg 4 # a [3:0] $end
$var reg 4 $ b [3:0] $end
$var reg 1 % carry_in $end
$var integer 32 & i [31:0] $end
$scope module uut $end
$var wire 4 ' a [3:0] $end
$var wire 4 ( b [3:0] $end
$var wire 1 % carry_in $end
$var wire 4 ) sum [3:0] $end
$var wire 1 " carry_out $end
$var wire 1 * c2 $end
$var wire 1 + c1 $end
$var wire 1 , c0 $end
$scope module fa0 $end
$var wire 1 - a $end
$var wire 1 . b $end
$var wire 1 % c $end
$var wire 1 , carry $end
$var wire 1 / sum $end
$upscope $end
$scope module fa1 $end
$var wire 1 0 a $end
$var wire 1 1 b $end
$var wire 1 % c $end
$var wire 1 + carry $end
$var wire 1 2 sum $end
$upscope $end
$scope module fa2 $end
$var wire 1 3 a $end
$var wire 1 4 b $end
$var wire 1 % c $end
$var wire 1 * carry $end
$var wire 1 5 sum $end
$upscope $end
$scope module fa3 $end
$var wire 1 6 a $end
$var wire 1 7 b $end
$var wire 1 % c $end
$var wire 1 " carry $end
$var wire 1 8 sum $end
$upscope $end
$upscope $end
$upscope $end
$enddefinitions $end
$comment Show the parameter values. $end
$dumpall
$end
#0
$dumpvars
08
07
06
05
04
03
02
01
00
0/
0.
0-
0,
0+
0*
b0 )
b0 (
b0 '
b0 &
0%
b0 $
b0 #
0"
b0 !
$end
#10
b1 !
b1 )
1/
1.
b1 $
b1 (
b1 &
#20
b10 !
b10 )
0/
12
0.
11
b10 $
b10 (
b10 &
#30
b11 !
b11 )
1/
1.
b11 $
b11 (
b11 &
#40
b100 !
b100 )
0/
02
15
0.
01
14
b100 $
b100 (
b100 &
#50
b101 !
b101 )
1/
1.
b101 $
b101 (
b101 &
#60
b110 !
b110 )
0/
12
0.
11
b110 $
b110 (
b110 &
#70
b111 !
b111 )
1/
1.
b111 $
b111 (
b111 &
#80
b1000 !
b1000 )
0/
02
05
18
0.
01
04
17
b1000 $
b1000 (
b1000 &
#90
b1001 !
b1001 )
1/
1.
b1001 $
b1001 (
b1001 &
#100
b1010 !
b1010 )
0/
12
0.
11
b1010 $
b1010 (
b1010 &
#110
b1011 !
b1011 )
1/
1.
b1011 $
b1011 (
b1011 &
#120
b1100 !
b1100 )
0/
02
15
0.
01
14
b1100 $
b1100 (
b1100 &
#130
b1101 !
b1101 )
1/
1.
b1101 $
b1101 (
b1101 &
#140
b1110 !
b1110 )
0/
12
0.
11
b1110 $
b1110 (
b1110 &
#150
b1111 !
b1111 )
1/
1.
b1111 $
b1111 (
b1111 &
#160
b1 !
b1 )
02
05
08
1-
0.
01
04
07
b1 #
b1 '
b0 $
b0 (
b10000 &
#170
b0 !
b0 )
1,
0/
1.
b1 $
b1 (
b10001 &
#180
b11 !
b11 )
0,
1/
12
0.
11
b10 $
b10 (
b10010 &
#190
b10 !
b10 )
1,
0/
1.
b11 $
b11 (
b10011 &
#200
b101 !
b101 )
0,
1/
02
15
0.
01
14
b100 $
b100 (
b10100 &
#210
b100 !
b100 )
1,
0/
1.
b101 $
b101 (
b10101 &
#220
b111 !
b111 )
0,
1/
12
0.
11
b110 $
b110 (
b10110 &
#230
b110 !
b110 )
1,
0/
1.
b111 $
b111 (
b10111 &
#240
b1001 !
b1001 )
0,
1/
02
05
18
0.
01
04
17
b1000 $
b1000 (
b11000 &
#250
b1000 !
b1000 )
1,
0/
1.
b1001 $
b1001 (
b11001 &
#260
b1011 !
b1011 )
0,
1/
12
0.
11
b1010 $
b1010 (
b11010 &
#270
b1010 !
b1010 )
1,
0/
1.
b1011 $
b1011 (
b11011 &
#280
b1101 !
b1101 )
0,
1/
02
15
0.
01
14
b1100 $
b1100 (
b11100 &
#290
b1100 !
b1100 )
1,
0/
1.
b1101 $
b1101 (
b11101 &
#300
b1111 !
b1111 )
0,
1/
12
0.
11
b1110 $
b1110 (
b11110 &
#310
b1110 !
b1110 )
1,
0/
1.
b1111 $
b1111 (
b11111 &
#320
b10 !
b10 )
0,
05
08
0-
10
0.
01
04
07
b10 #
b10 '
b0 $
b0 (
b100000 &
#330
b11 !
b11 )
1/
1.
b1 $
b1 (
b100001 &
#340
b0 !
b0 )
0/
1+
02
0.
11
b10 $
b10 (
b100010 &
#350
b1 !
b1 )
1/
1.
b11 $
b11 (
b100011 &
#360
b110 !
b110 )
0/
0+
12
15
0.
01
14
b100 $
b100 (
b100100 &
#370
b111 !
b111 )
1/
1.
b101 $
b101 (
b100101 &
#380
b100 !
b100 )
0/
1+
02
0.
11
b110 $
b110 (
b100110 &
#390
b101 !
b101 )
1/
1.
b111 $
b111 (
b100111 &
#400
b1010 !
b1010 )
0/
0+
12
05
18
0.
01
04
17
b1000 $
b1000 (
b101000 &
#410
b1011 !
b1011 )
1/
1.
b1001 $
b1001 (
b101001 &
#420
b1000 !
b1000 )
0/
1+
02
0.
11
b1010 $
b1010 (
b101010 &
#430
b1001 !
b1001 )
1/
1.
b1011 $
b1011 (
b101011 &
#440
b1110 !
b1110 )
0/
0+
12
15
0.
01
14
b1100 $
b1100 (
b101100 &
#450
b1111 !
b1111 )
1/
1.
b1101 $
b1101 (
b101101 &
#460
b1100 !
b1100 )
0/
1+
02
0.
11
b1110 $
b1110 (
b101110 &
#470
b1101 !
b1101 )
1/
1.
b1111 $
b1111 (
b101111 &
#480
b11 !
b11 )
0+
12
05
08
1-
0.
01
04
07
b11 #
b11 '
b0 $
b0 (
b110000 &
#490
b10 !
b10 )
1,
0/
1.
b1 $
b1 (
b110001 &
#500
b1 !
b1 )
0,
1/
1+
02
0.
11
b10 $
b10 (
b110010 &
#510
b0 !
b0 )
1,
0/
1.
b11 $
b11 (
b110011 &
#520
b111 !
b111 )
0,
1/
0+
12
15
0.
01
14
b100 $
b100 (
b110100 &
#530
b110 !
b110 )
1,
0/
1.
b101 $
b101 (
b110101 &
#540
b101 !
b101 )
0,
1/
1+
02
0.
11
b110 $
b110 (
b110110 &
#550
b100 !
b100 )
1,
0/
1.
b111 $
b111 (
b110111 &
#560
b1011 !
b1011 )
0,
1/
0+
12
05
18
0.
01
04
17
b1000 $
b1000 (
b111000 &
#570
b1010 !
b1010 )
1,
0/
1.
b1001 $
b1001 (
b111001 &
#580
b1001 !
b1001 )
0,
1/
1+
02
0.
11
b1010 $
b1010 (
b111010 &
#590
b1000 !
b1000 )
1,
0/
1.
b1011 $
b1011 (
b111011 &
#600
b1111 !
b1111 )
0,
1/
0+
12
15
0.
01
14
b1100 $
b1100 (
b111100 &
#610
b1110 !
b1110 )
1,
0/
1.
b1101 $
b1101 (
b111101 &
#620
b1101 !
b1101 )
0,
1/
1+
02
0.
11
b1110 $
b1110 (
b111110 &
#630
b1100 !
b1100 )
1,
0/
1.
b1111 $
b1111 (
b111111 &
#640
b100 !
b100 )
0,
0+
08
0-
00
13
0.
01
04
07
b100 #
b100 '
b0 $
b0 (
b1000000 &
#650
b101 !
b101 )
1/
1.
b1 $
b1 (
b1000001 &
#660
b110 !
b110 )
0/
12
0.
11
b10 $
b10 (
b1000010 &
#670
b111 !
b111 )
1/
1.
b11 $
b11 (
b1000011 &
#680
b0 !
b0 )
0/
02
1*
05
0.
01
14
b100 $
b100 (
b1000100 &
#690
b1 !
b1 )
1/
1.
b101 $
b101 (
b1000101 &
#700
b10 !
b10 )
0/
12
0.
11
b110 $
b110 (
b1000110 &
#710
b11 !
b11 )
1/
1.
b111 $
b111 (
b1000111 &
#720
b1100 !
b1100 )
0/
02
0*
15
18
0.
01
04
17
b1000 $
b1000 (
b1001000 &
#730
b1101 !
b1101 )
1/
1.
b1001 $
b1001 (
b1001001 &
#740
b1110 !
b1110 )
0/
12
0.
11
b1010 $
b1010 (
b1001010 &
#750
b1111 !
b1111 )
1/
1.
b1011 $
b1011 (
b1001011 &
#760
b1000 !
b1000 )
0/
02
1*
05
0.
01
14
b1100 $
b1100 (
b1001100 &
#770
b1001 !
b1001 )
1/
1.
b1101 $
b1101 (
b1001101 &
#780
b1010 !
b1010 )
0/
12
0.
11
b1110 $
b1110 (
b1001110 &
#790
b1011 !
b1011 )
1/
1.
b1111 $
b1111 (
b1001111 &
#800
b101 !
b101 )
02
0*
15
08
1-
0.
01
04
07
b101 #
b101 '
b0 $
b0 (
b1010000 &
#810
b100 !
b100 )
1,
0/
1.
b1 $
b1 (
b1010001 &
#820
b111 !
b111 )
0,
1/
12
0.
11
b10 $
b10 (
b1010010 &
#830
b110 !
b110 )
1,
0/
1.
b11 $
b11 (
b1010011 &
#840
b1 !
b1 )
0,
1/
02
1*
05
0.
01
14
b100 $
b100 (
b1010100 &
#850
b0 !
b0 )
1,
0/
1.
b101 $
b101 (
b1010101 &
#860
b11 !
b11 )
0,
1/
12
0.
11
b110 $
b110 (
b1010110 &
#870
b10 !
b10 )
1,
0/
1.
b111 $
b111 (
b1010111 &
#880
b1101 !
b1101 )
0,
1/
02
0*
15
18
0.
01
04
17
b1000 $
b1000 (
b1011000 &
#890
b1100 !
b1100 )
1,
0/
1.
b1001 $
b1001 (
b1011001 &
#900
b1111 !
b1111 )
0,
1/
12
0.
11
b1010 $
b1010 (
b1011010 &
#910
b1110 !
b1110 )
1,
0/
1.
b1011 $
b1011 (
b1011011 &
#920
b1001 !
b1001 )
0,
1/
02
1*
05
0.
01
14
b1100 $
b1100 (
b1011100 &
#930
b1000 !
b1000 )
1,
0/
1.
b1101 $
b1101 (
b1011101 &
#940
b1011 !
b1011 )
0,
1/
12
0.
11
b1110 $
b1110 (
b1011110 &
#950
b1010 !
b1010 )
1,
0/
1.
b1111 $
b1111 (
b1011111 &
#960
b110 !
b110 )
0,
0*
15
08
0-
10
0.
01
04
07
b110 #
b110 '
b0 $
b0 (
b1100000 &
#970
b111 !
b111 )
1/
1.
b1 $
b1 (
b1100001 &
#980
b100 !
b100 )
0/
1+
02
0.
11
b10 $
b10 (
b1100010 &
#990
b101 !
b101 )
1/
1.
b11 $
b11 (
b1100011 &
#1000
b10 !
b10 )
0/
0+
12
1*
05
0.
01
14
b100 $
b100 (
b1100100 &
#1010
b11 !
b11 )
1/
1.
b101 $
b101 (
b1100101 &
#1020
b0 !
b0 )
0/
1+
02
0.
11
b110 $
b110 (
b1100110 &
#1030
b1 !
b1 )
1/
1.
b111 $
b111 (
b1100111 &
#1040
b1110 !
b1110 )
0/
0+
12
0*
15
18
0.
01
04
17
b1000 $
b1000 (
b1101000 &
#1050
b1111 !
b1111 )
1/
1.
b1001 $
b1001 (
b1101001 &
#1060
b1100 !
b1100 )
0/
1+
02
0.
11
b1010 $
b1010 (
b1101010 &
#1070
b1101 !
b1101 )
1/
1.
b1011 $
b1011 (
b1101011 &
#1080
b1010 !
b1010 )
0/
0+
12
1*
05
0.
01
14
b1100 $
b1100 (
b1101100 &
#1090
b1011 !
b1011 )
1/
1.
b1101 $
b1101 (
b1101101 &
#1100
b1000 !
b1000 )
0/
1+
02
0.
11
b1110 $
b1110 (
b1101110 &
#1110
b1001 !
b1001 )
1/
1.
b1111 $
b1111 (
b1101111 &
#1120
b111 !
b111 )
0+
12
0*
15
08
1-
0.
01
04
07
b111 #
b111 '
b0 $
b0 (
b1110000 &
#1130
b110 !
b110 )
1,
0/
1.
b1 $
b1 (
b1110001 &
#1140
b101 !
b101 )
0,
1/
1+
02
0.
11
b10 $
b10 (
b1110010 &
#1150
b100 !
b100 )
1,
0/
1.
b11 $
b11 (
b1110011 &
#1160
b11 !
b11 )
0,
1/
0+
12
1*
05
0.
01
14
b100 $
b100 (
b1110100 &
#1170
b10 !
b10 )
1,
0/
1.
b101 $
b101 (
b1110101 &
#1180
b1 !
b1 )
0,
1/
1+
02
0.
11
b110 $
b110 (
b1110110 &
#1190
b0 !
b0 )
1,
0/
1.
b111 $
b111 (
b1110111 &
#1200
b1111 !
b1111 )
0,
1/
0+
12
0*
15
18
0.
01
04
17
b1000 $
b1000 (
b1111000 &
#1210
b1110 !
b1110 )
1,
0/
1.
b1001 $
b1001 (
b1111001 &
#1220
b1101 !
b1101 )
0,
1/
1+
02
0.
11
b1010 $
b1010 (
b1111010 &
#1230
b1100 !
b1100 )
1,
0/
1.
b1011 $
b1011 (
b1111011 &
#1240
b1011 !
b1011 )
0,
1/
0+
12
1*
05
0.
01
14
b1100 $
b1100 (
b1111100 &
#1250
b1010 !
b1010 )
1,
0/
1.
b1101 $
b1101 (
b1111101 &
#1260
b1001 !
b1001 )
0,
1/
1+
02
0.
11
b1110 $
b1110 (
b1111110 &
#1270
b1000 !
b1000 )
1,
0/
1.
b1111 $
b1111 (
b1111111 &
#1280
0,
0+
0*
0-
00
03
16
0.
01
04
07
b1000 #
b1000 '
b0 $
b0 (
b10000000 &
#1290
b1001 !
b1001 )
1/
1.
b1 $
b1 (
b10000001 &
#1300
b1010 !
b1010 )
0/
12
0.
11
b10 $
b10 (
b10000010 &
#1310
b1011 !
b1011 )
1/
1.
b11 $
b11 (
b10000011 &
#1320
b1100 !
b1100 )
0/
02
15
0.
01
14
b100 $
b100 (
b10000100 &
#1330
b1101 !
b1101 )
1/
1.
b101 $
b101 (
b10000101 &
#1340
b1110 !
b1110 )
0/
12
0.
11
b110 $
b110 (
b10000110 &
#1350
b1111 !
b1111 )
1/
1.
b111 $
b111 (
b10000111 &
#1360
b0 !
b0 )
0/
02
05
1"
08
0.
01
04
17
b1000 $
b1000 (
b10001000 &
#1370
b1 !
b1 )
1/
1.
b1001 $
b1001 (
b10001001 &
#1380
b10 !
b10 )
0/
12
0.
11
b1010 $
b1010 (
b10001010 &
#1390
b11 !
b11 )
1/
1.
b1011 $
b1011 (
b10001011 &
#1400
b100 !
b100 )
0/
02
15
0.
01
14
b1100 $
b1100 (
b10001100 &
#1410
b101 !
b101 )
1/
1.
b1101 $
b1101 (
b10001101 &
#1420
b110 !
b110 )
0/
12
0.
11
b1110 $
b1110 (
b10001110 &
#1430
b111 !
b111 )
1/
1.
b1111 $
b1111 (
b10001111 &
#1440
b1001 !
b1001 )
02
05
0"
18
1-
0.
01
04
07
b1001 #
b1001 '
b0 $
b0 (
b10010000 &
#1450
b1000 !
b1000 )
1,
0/
1.
b1 $
b1 (
b10010001 &
#1460
b1011 !
b1011 )
0,
1/
12
0.
11
b10 $
b10 (
b10010010 &
#1470
b1010 !
b1010 )
1,
0/
1.
b11 $
b11 (
b10010011 &
#1480
b1101 !
b1101 )
0,
1/
02
15
0.
01
14
b100 $
b100 (
b10010100 &
#1490
b1100 !
b1100 )
1,
0/
1.
b101 $
b101 (
b10010101 &
#1500
b1111 !
b1111 )
0,
1/
12
0.
11
b110 $
b110 (
b10010110 &
#1510
b1110 !
b1110 )
1,
0/
1.
b111 $
b111 (
b10010111 &
#1520
b1 !
b1 )
0,
1/
02
05
1"
08
0.
01
04
17
b1000 $
b1000 (
b10011000 &
#1530
b0 !
b0 )
1,
0/
1.
b1001 $
b1001 (
b10011001 &
#1540
b11 !
b11 )
0,
1/
12
0.
11
b1010 $
b1010 (
b10011010 &
#1550
b10 !
b10 )
1,
0/
1.
b1011 $
b1011 (
b10011011 &
#1560
b101 !
b101 )
0,
1/
02
15
0.
01
14
b1100 $
b1100 (
b10011100 &
#1570
b100 !
b100 )
1,
0/
1.
b1101 $
b1101 (
b10011101 &
#1580
b111 !
b111 )
0,
1/
12
0.
11
b1110 $
b1110 (
b10011110 &
#1590
b110 !
b110 )
1,
0/
1.
b1111 $
b1111 (
b10011111 &
#1600
b1010 !
b1010 )
0,
05
0"
18
0-
10
0.
01
04
07
b1010 #
b1010 '
b0 $
b0 (
b10100000 &
#1610
b1011 !
b1011 )
1/
1.
b1 $
b1 (
b10100001 &
#1620
b1000 !
b1000 )
0/
1+
02
0.
11
b10 $
b10 (
b10100010 &
#1630
b1001 !
b1001 )
1/
1.
b11 $
b11 (
b10100011 &
#1640
b1110 !
b1110 )
0/
0+
12
15
0.
01
14
b100 $
b100 (
b10100100 &
#1650
b1111 !
b1111 )
1/
1.
b101 $
b101 (
b10100101 &
#1660
b1100 !
b1100 )
0/
1+
02
0.
11
b110 $
b110 (
b10100110 &
#1670
b1101 !
b1101 )
1/
1.
b111 $
b111 (
b10100111 &
#1680
b10 !
b10 )
0/
0+
12
05
1"
08
0.
01
04
17
b1000 $
b1000 (
b10101000 &
#1690
b11 !
b11 )
1/
1.
b1001 $
b1001 (
b10101001 &
#1700
b0 !
b0 )
0/
1+
02
0.
11
b1010 $
b1010 (
b10101010 &
#1710
b1 !
b1 )
1/
1.
b1011 $
b1011 (
b10101011 &
#1720
b110 !
b110 )
0/
0+
12
15
0.
01
14
b1100 $
b1100 (
b10101100 &
#1730
b111 !
b111 )
1/
1.
b1101 $
b1101 (
b10101101 &
#1740
b100 !
b100 )
0/
1+
02
0.
11
b1110 $
b1110 (
b10101110 &
#1750
b101 !
b101 )
1/
1.
b1111 $
b1111 (
b10101111 &
#1760
b1011 !
b1011 )
0+
12
05
0"
18
1-
0.
01
04
07
b1011 #
b1011 '
b0 $
b0 (
b10110000 &
#1770
b1010 !
b1010 )
1,
0/
1.
b1 $
b1 (
b10110001 &
#1780
b1001 !
b1001 )
0,
1/
1+
02
0.
11
b10 $
b10 (
b10110010 &
#1790
b1000 !
b1000 )
1,
0/
1.
b11 $
b11 (
b10110011 &
#1800
b1111 !
b1111 )
0,
1/
0+
12
15
0.
01
14
b100 $
b100 (
b10110100 &
#1810
b1110 !
b1110 )
1,
0/
1.
b101 $
b101 (
b10110101 &
#1820
b1101 !
b1101 )
0,
1/
1+
02
0.
11
b110 $
b110 (
b10110110 &
#1830
b1100 !
b1100 )
1,
0/
1.
b111 $
b111 (
b10110111 &
#1840
b11 !
b11 )
0,
1/
0+
12
05
1"
08
0.
01
04
17
b1000 $
b1000 (
b10111000 &
#1850
b10 !
b10 )
1,
0/
1.
b1001 $
b1001 (
b10111001 &
#1860
b1 !
b1 )
0,
1/
1+
02
0.
11
b1010 $
b1010 (
b10111010 &
#1870
b0 !
b0 )
1,
0/
1.
b1011 $
b1011 (
b10111011 &
#1880
b111 !
b111 )
0,
1/
0+
12
15
0.
01
14
b1100 $
b1100 (
b10111100 &
#1890
b110 !
b110 )
1,
0/
1.
b1101 $
b1101 (
b10111101 &
#1900
b101 !
b101 )
0,
1/
1+
02
0.
11
b1110 $
b1110 (
b10111110 &
#1910
b100 !
b100 )
1,
0/
1.
b1111 $
b1111 (
b10111111 &
#1920
b1100 !
b1100 )
0,
0+
0"
18
0-
00
13
0.
01
04
07
b1100 #
b1100 '
b0 $
b0 (
b11000000 &
#1930
b1101 !
b1101 )
1/
1.
b1 $
b1 (
b11000001 &
#1940
b1110 !
b1110 )
0/
12
0.
11
b10 $
b10 (
b11000010 &
#1950
b1111 !
b1111 )
1/
1.
b11 $
b11 (
b11000011 &
#1960
b1000 !
b1000 )
0/
02
1*
05
0.
01
14
b100 $
b100 (
b11000100 &
#1970
b1001 !
b1001 )
1/
1.
b101 $
b101 (
b11000101 &
#1980
b1010 !
b1010 )
0/
12
0.
11
b110 $
b110 (
b11000110 &
#1990
b1011 !
b1011 )
1/
1.
b111 $
b111 (
b11000111 &
#2000
b100 !
b100 )
0/
02
0*
15
1"
08
0.
01
04
17
b1000 $
b1000 (
b11001000 &
#2010
b101 !
b101 )
1/
1.
b1001 $
b1001 (
b11001001 &
#2020
b110 !
b110 )
0/
12
0.
11
b1010 $
b1010 (
b11001010 &
#2030
b111 !
b111 )
1/
1.
b1011 $
b1011 (
b11001011 &
#2040
b0 !
b0 )
0/
02
1*
05
0.
01
14
b1100 $
b1100 (
b11001100 &
#2050
b1 !
b1 )
1/
1.
b1101 $
b1101 (
b11001101 &
#2060
b10 !
b10 )
0/
12
0.
11
b1110 $
b1110 (
b11001110 &
#2070
b11 !
b11 )
1/
1.
b1111 $
b1111 (
b11001111 &
#2080
b1101 !
b1101 )
02
0*
15
0"
18
1-
0.
01
04
07
b1101 #
b1101 '
b0 $
b0 (
b11010000 &
#2090
b1100 !
b1100 )
1,
0/
1.
b1 $
b1 (
b11010001 &
#2100
b1111 !
b1111 )
0,
1/
12
0.
11
b10 $
b10 (
b11010010 &
#2110
b1110 !
b1110 )
1,
0/
1.
b11 $
b11 (
b11010011 &
#2120
b1001 !
b1001 )
0,
1/
02
1*
05
0.
01
14
b100 $
b100 (
b11010100 &
#2130
b1000 !
b1000 )
1,
0/
1.
b101 $
b101 (
b11010101 &
#2140
b1011 !
b1011 )
0,
1/
12
0.
11
b110 $
b110 (
b11010110 &
#2150
b1010 !
b1010 )
1,
0/
1.
b111 $
b111 (
b11010111 &
#2160
b101 !
b101 )
0,
1/
02
0*
15
1"
08
0.
01
04
17
b1000 $
b1000 (
b11011000 &
#2170
b100 !
b100 )
1,
0/
1.
b1001 $
b1001 (
b11011001 &
#2180
b111 !
b111 )
0,
1/
12
0.
11
b1010 $
b1010 (
b11011010 &
#2190
b110 !
b110 )
1,
0/
1.
b1011 $
b1011 (
b11011011 &
#2200
b1 !
b1 )
0,
1/
02
1*
05
0.
01
14
b1100 $
b1100 (
b11011100 &
#2210
b0 !
b0 )
1,
0/
1.
b1101 $
b1101 (
b11011101 &
#2220
b11 !
b11 )
0,
1/
12
0.
11
b1110 $
b1110 (
b11011110 &
#2230
b10 !
b10 )
1,
0/
1.
b1111 $
b1111 (
b11011111 &
#2240
b1110 !
b1110 )
0,
0*
15
0"
18
0-
10
0.
01
04
07
b1110 #
b1110 '
b0 $
b0 (
b11100000 &
#2250
b1111 !
b1111 )
1/
1.
b1 $
b1 (
b11100001 &
#2260
b1100 !
b1100 )
0/
1+
02
0.
11
b10 $
b10 (
b11100010 &
#2270
b1101 !
b1101 )
1/
1.
b11 $
b11 (
b11100011 &
#2280
b1010 !
b1010 )
0/
0+
12
1*
05
0.
01
14
b100 $
b100 (
b11100100 &
#2290
b1011 !
b1011 )
1/
1.
b101 $
b101 (
b11100101 &
#2300
b1000 !
b1000 )
0/
1+
02
0.
11
b110 $
b110 (
b11100110 &
#2310
b1001 !
b1001 )
1/
1.
b111 $
b111 (
b11100111 &
#2320
b110 !
b110 )
0/
0+
12
0*
15
1"
08
0.
01
04
17
b1000 $
b1000 (
b11101000 &
#2330
b111 !
b111 )
1/
1.
b1001 $
b1001 (
b11101001 &
#2340
b100 !
b100 )
0/
1+
02
0.
11
b1010 $
b1010 (
b11101010 &
#2350
b101 !
b101 )
1/
1.
b1011 $
b1011 (
b11101011 &
#2360
b10 !
b10 )
0/
0+
12
1*
05
0.
01
14
b1100 $
b1100 (
b11101100 &
#2370
b11 !
b11 )
1/
1.
b1101 $
b1101 (
b11101101 &
#2380
b0 !
b0 )
0/
1+
02
0.
11
b1110 $
b1110 (
b11101110 &
#2390
b1 !
b1 )
1/
1.
b1111 $
b1111 (
b11101111 &
#2400
b1111 !
b1111 )
0+
12
0*
15
0"
18
1-
0.
01
04
07
b1111 #
b1111 '
b0 $
b0 (
b11110000 &
#2410
b1110 !
b1110 )
1,
0/
1.
b1 $
b1 (
b11110001 &
#2420
b1101 !
b1101 )
0,
1/
1+
02
0.
11
b10 $
b10 (
b11110010 &
#2430
b1100 !
b1100 )
1,
0/
1.
b11 $
b11 (
b11110011 &
#2440
b1011 !
b1011 )
0,
1/
0+
12
1*
05
0.
01
14
b100 $
b100 (
b11110100 &
#2450
b1010 !
b1010 )
1,
0/
1.
b101 $
b101 (
b11110101 &
#2460
b1001 !
b1001 )
0,
1/
1+
02
0.
11
b110 $
b110 (
b11110110 &
#2470
b1000 !
b1000 )
1,
0/
1.
b111 $
b111 (
b11110111 &
#2480
b111 !
b111 )
0,
1/
0+
12
0*
15
1"
08
0.
01
04
17
b1000 $
b1000 (
b11111000 &
#2490
b110 !
b110 )
1,
0/
1.
b1001 $
b1001 (
b11111001 &
#2500
b101 !
b101 )
0,
1/
1+
02
0.
11
b1010 $
b1010 (
b11111010 &
#2510
b100 !
b100 )
1,
0/
1.
b1011 $
b1011 (
b11111011 &
#2520
b11 !
b11 )
0,
1/
0+
12
1*
05
0.
01
14
b1100 $
b1100 (
b11111100 &
#2530
b10 !
b10 )
1,
0/
1.
b1101 $
b1101 (
b11111101 &
#2540
b1 !
b1 )
0,
1/
1+
02
0.
11
b1110 $
b1110 (
b11111110 &
#2550
b0 !
b0 )
1,
0/
1.
b1111 $
b1111 (
b11111111 &
#2560
0,
0+
0*
0"
b1111 !
b1111 )
1/
12
15
18
0-
00
03
06
0.
01
04
07
1%
b0 #
b0 '
b0 $
b0 (
b100000000 &
#2570
1,
b1110 !
b1110 )
0/
1.
b1 $
b1 (
b100000001 &
#2580
0,
1+
b1101 !
b1101 )
1/
02
0.
11
b10 $
b10 (
b100000010 &
#2590
1,
b1100 !
b1100 )
0/
1.
b11 $
b11 (
b100000011 &
#2600
0,
0+
1*
b1011 !
b1011 )
1/
12
05
0.
01
14
b100 $
b100 (
b100000100 &
#2610
1,
b1010 !
b1010 )
0/
1.
b101 $
b101 (
b100000101 &
#2620
0,
1+
b1001 !
b1001 )
1/
02
0.
11
b110 $
b110 (
b100000110 &
#2630
1,
b1000 !
b1000 )
0/
1.
b111 $
b111 (
b100000111 &
#2640
0,
0+
0*
1"
b111 !
b111 )
1/
12
15
08
0.
01
04
17
b1000 $
b1000 (
b100001000 &
#2650
1,
b110 !
b110 )
0/
1.
b1001 $
b1001 (
b100001001 &
#2660
0,
1+
b101 !
b101 )
1/
02
0.
11
b1010 $
b1010 (
b100001010 &
#2670
1,
b100 !
b100 )
0/
1.
b1011 $
b1011 (
b100001011 &
#2680
0,
0+
1*
b11 !
b11 )
1/
12
05
0.
01
14
b1100 $
b1100 (
b100001100 &
#2690
1,
b10 !
b10 )
0/
1.
b1101 $
b1101 (
b100001101 &
#2700
0,
1+
b1 !
b1 )
1/
02
0.
11
b1110 $
b1110 (
b100001110 &
#2710
1,
b0 !
b0 )
0/
1.
b1111 $
b1111 (
b100001111 &
#2720
0+
0*
0"
b1110 !
b1110 )
12
15
18
1-
0.
01
04
07
b1 #
b1 '
b0 $
b0 (
b100010000 &
#2730
b1111 !
b1111 )
1/
1.
b1 $
b1 (
b100010001 &
#2740
1+
b1100 !
b1100 )
1,
0/
02
0.
11
b10 $
b10 (
b100010010 &
#2750
b1101 !
b1101 )
1/
1.
b11 $
b11 (
b100010011 &
#2760
0+
1*
b1010 !
b1010 )
1,
0/
12
05
0.
01
14
b100 $
b100 (
b100010100 &
#2770
b1011 !
b1011 )
1/
1.
b101 $
b101 (
b100010101 &
#2780
1+
b1000 !
b1000 )
1,
0/
02
0.
11
b110 $
b110 (
b100010110 &
#2790
b1001 !
b1001 )
1/
1.
b111 $
b111 (
b100010111 &
#2800
0+
0*
1"
b110 !
b110 )
1,
0/
12
15
08
0.
01
04
17
b1000 $
b1000 (
b100011000 &
#2810
b111 !
b111 )
1/
1.
b1001 $
b1001 (
b100011001 &
#2820
1+
b100 !
b100 )
1,
0/
02
0.
11
b1010 $
b1010 (
b100011010 &
#2830
b101 !
b101 )
1/
1.
b1011 $
b1011 (
b100011011 &
#2840
0+
1*
b10 !
b10 )
1,
0/
12
05
0.
01
14
b1100 $
b1100 (
b100011100 &
#2850
b11 !
b11 )
1/
1.
b1101 $
b1101 (
b100011101 &
#2860
1+
b0 !
b0 )
1,
0/
02
0.
11
b1110 $
b1110 (
b100011110 &
#2870
b1 !
b1 )
1/
1.
b1111 $
b1111 (
b100011111 &
#2880
0*
0"
b1101 !
b1101 )
0,
15
18
0-
10
0.
01
04
07
b10 #
b10 '
b0 $
b0 (
b100100000 &
#2890
1,
b1100 !
b1100 )
0/
1.
b1 $
b1 (
b100100001 &
#2900
0,
b1111 !
b1111 )
1/
12
0.
11
b10 $
b10 (
b100100010 &
#2910
1,
b1110 !
b1110 )
0/
1.
b11 $
b11 (
b100100011 &
#2920
0,
1*
b1001 !
b1001 )
1/
1+
02
05
0.
01
14
b100 $
b100 (
b100100100 &
#2930
1,
b1000 !
b1000 )
0/
1.
b101 $
b101 (
b100100101 &
#2940
0,
b1011 !
b1011 )
1/
12
0.
11
b110 $
b110 (
b100100110 &
