learning_verilog/Digit_Counter/digit_counter.v
module digit_counter
(
    input clk, rst,
    output reg [1:0] sel
);

    always @(posedge clk) begin
        if(rst) begin
            sel <= 2'b00; 
        end
        else begin
            sel <= sel + 1; 
        end
    end


endmodule

Learning Verilog/Digit_Counter/digit_counter_tb.v
module digit_counter_tb();

    reg rst, clk; 
    wire [1:0] sel; 

    digit_counter uut
    (
        .rst(rst),
        .clk(clk),
        .sel(sel)
    );

    initial begin
        clk = 0; 
        forever #5 clk = ~clk; 
    end


    initial begin

        $dumpfile("digit_counter.vcd");
        $dumpvars(0, digit_counter_tb);

        rst = 1; #10; 
        rst = 0; #100; 

        $finish; 
    end


endmodule

Digit_Counter/digit_counter.vcd
$date
	Sat Jun 20 01:33:18 2026
$end
$version
	Icarus Verilog
$end
$timescale
	1s
$end
$scope module digit_counter_tb $end
$var wire 2 ! sel [1:0] $end
$var reg 1 " clk $end
$var reg 1 # rst $end
$scope module uut $end
$var wire 1 " clk $end
$var wire 1 # rst $end
$var reg 2 $ sel [1:0] $end
$upscope $end
$upscope $end
$enddefinitions $end
$comment Show the parameter values. $end
$dumpall
$end
#0
$dumpvars
bx $
1#
0"
bx !
$end
#5
b0 !
b0 $
1"
#10
0"
0#
#15
b1 !
b1 $
1"
#20
0"
#25
b10 !
b10 $
1"
#30
0"
#35
b11 !
b11 $
1"
#40
0"
#45
b0 !
b0 $
1"
#50
0"
#55
b1 !
b1 $
1"
#60
0"
#65
b10 !
b10 $
1"
#70
0"
#75
b11 !
b11 $
1"
#80
0"
#85
b0 !
b0 $
1"
#90
0"
#95
b1 !
b1 $
1"
#100
0"
#105
b10 !
b10 $
1"
