Full_Adder/full_adder.v
module full_adder 
(
    input a, b, c,
    output carry, sum //assigning inputs and outputs 
);
    assign carry = ((a ^ b) & c) | (a & b); //makign carry eqaul to the carry bool equation 
    assign sum = ((a ^ b) ^ c); //making sum equal to the sum bool equation for full adder
endmodule

Full_Adder/full_adder_tb.v
module full_adder_tb;

    reg a, b, c; 
    wire sum, carry; 

    full_adder uut
    (
        .a(a), 
        .b(b), 
        .c(c), 
        .sum(sum),
        .carry(carry)
    );

    initial begin

        $dumpfile("full_adder.vcd");
        $dumpvars(0, full_adder_tb);

        a = 0; b = 0; c = 0; #10; 
        a = 0; b = 0; c = 1; #10; 
        a = 0; b = 1; c = 0; #10; 
        a = 0; b = 1; c = 1; #10; 
        a = 1; b = 0; c = 0; #10; 
        a = 1; b = 0; c = 1; #10; 
        a = 1; b = 1; c = 0; #10; 
        a = 1; b = 1; c = 1; #10; 

        $finish;

    end

endmodule

Full_Adder/full_adder.vcd
$date
	Tue Jun 16 23:42:00 2026
$end
$version
	Icarus Verilog
$end
$timescale
	1s
$end
$scope module full_adder_tb $end
$var wire 1 ! sum $end
$var wire 1 " carry $end
$var reg 1 # a $end
$var reg 1 $ b $end
$var reg 1 % c $end
$scope module uut $end
$var wire 1 # a $end
$var wire 1 $ b $end
$var wire 1 % c $end
$var wire 1 " carry $end
$var wire 1 ! sum $end
$upscope $end
$upscope $end
$enddefinitions $end
$comment Show the parameter values. $end
$dumpall
$end
#0
$dumpvars
0%
0$
0#
0"
0!
$end
#10
1!
1%
#20
0%
1$
#30
1"
0!
1%
#40
0"
1!
0%
0$
1#
#50
1"
0!
1%
#60
0%
1$
#70
1!
1%
